README.rst
setup.py
binary_pairs/__init__.py
binary_pairs.egg-info/PKG-INFO
binary_pairs.egg-info/SOURCES.txt
binary_pairs.egg-info/dependency_links.txt
binary_pairs.egg-info/requires.txt
binary_pairs.egg-info/top_level.txt
utils/binary-pairs