Metadata-Version: 1.1
Name: binary-pairs
Version: 0.0.3
Summary: Utility designed for check combinations of multiple binary params
Home-page: https://github.com/strizhechenko/binary-pairs
Author: Oleg Strizhechenko
Author-email: oleg.strizhechenko@gmail.com
License: GPL
Keywords: combinatoric testing utils fuzz pairwise nwise reduce
Platform: UNKNOWN
Classifier: Development Status :: 3 - Alpha
Classifier: Intended Audience :: Developers
Classifier: Operating System :: MacOS
Classifier: Operating System :: POSIX
Classifier: Programming Language :: Python
Classifier: Programming Language :: Python :: 2
Classifier: Topic :: Software Development
Classifier: Topic :: Utilities
